__init__.py
sinapsis_llama_index/__init__.py
sinapsis_llama_index/helpers/__init__.py
sinapsis_llama_index/helpers/llama_index_pg_retriever.py
sinapsis_llama_index/helpers/pgvector_helpers.py
sinapsis_llama_index/helpers/rag_env_vars.py
sinapsis_llama_index/helpers/schemas.py
sinapsis_llama_index/templates/__init__.py
sinapsis_llama_index/templates/code_embedding_node_generator.py
sinapsis_llama_index/templates/embedding_node_generator.py
sinapsis_llama_index/templates/llama_index_clear_table.py
sinapsis_llama_index/templates/llama_index_delete_table.py
sinapsis_llama_index/templates/llama_index_insert_nodes.py
sinapsis_llama_index/templates/llama_index_node_retriever.py
sinapsis_llama_index/templates/llama_index_rag_text_completion.py
sinapsis_llama_index-0.1.13.dist-info/licenses/LICENSE
sinapsis_llama_index-0.1.13.dist-info/METADATA
sinapsis_llama_index-0.1.13.dist-info/WHEEL
sinapsis_llama_index-0.1.13.dist-info/top_level.txt
sinapsis_llama_index-0.1.13.dist-info/RECORD
