Metadata-Version: 2.4
Name: sinapsis-llama-index
Version: 0.1.13
Summary: Sinapsis templates and helpers for LlamaIndex integration.
Author-email: SinapsisAI <dev@sinapsis.tech>
Project-URL: Homepage, https://sinapsis.tech
Project-URL: Documentation, https://docs.sinapsis.tech/docs
Project-URL: Tutorials, https://docs.sinapsis.tech/tutorials
Project-URL: Repository, https://github.com/Sinapsis-AI/sinapsis-chatbots.git
Requires-Python: >=3.10
License-File: LICENSE
Requires-Dist: llama-index>=0.12.25
Requires-Dist: llama-index-embeddings-huggingface>=0.5.2
Requires-Dist: llama-index-legacy>=0.9.48.post4
Requires-Dist: llama-index-vector-stores-postgres>=0.4.2
Requires-Dist: llamaindex-py-client>=0.1.19
Requires-Dist: psycopg>=3.2.12
Requires-Dist: sinapsis>=0.2.0
Requires-Dist: sinapsis-chatbots-base
Requires-Dist: tree-sitter-language-pack>=0.8.0
Provides-Extra: sinapsis-llama-cpp
Requires-Dist: sinapsis-llama-cpp; extra == "sinapsis-llama-cpp"
Provides-Extra: chatbot
Requires-Dist: sinapsis-llama-cpp[chatbot]; extra == "chatbot"
Requires-Dist: einops>=0.8.1; extra == "chatbot"
Provides-Extra: xformers
Requires-Dist: triton; extra == "xformers"
Requires-Dist: setuptools>=78.1.0; extra == "xformers"
Requires-Dist: xformers>=0.0.29.post1; extra == "xformers"
Provides-Extra: all
Requires-Dist: sinapsis-llama-index[chatbot,xformers]; extra == "all"
Dynamic: license-file
